mkdocs_no_3rd_party/__init__.py
mkdocs_no_3rd_party/plugin.py
mkdocs_no_3rd_party_plugin-0.0.1.dist-info/LICENSE
mkdocs_no_3rd_party_plugin-0.0.1.dist-info/METADATA
mkdocs_no_3rd_party_plugin-0.0.1.dist-info/WHEEL
mkdocs_no_3rd_party_plugin-0.0.1.dist-info/entry_points.txt
mkdocs_no_3rd_party_plugin-0.0.1.dist-info/top_level.txt
mkdocs_no_3rd_party_plugin-0.0.1.dist-info/RECORD
