Metadata-Version: 2.1
Name: mkdocs-no-3rd-party-plugin
Version: 0.0.1
Summary: An MkDocs plugin to remove 3rd party assets and download them locally
Home-page: https://github.com/rany2/mkdocs-no-3rd-party-plugin
Author: rany
Author-email: rany2@riseup.net
License: MIT
Keywords: mkdocs privacy
Platform: UNKNOWN
Classifier: Development Status :: 4 - Beta
Classifier: Intended Audience :: Developers
Classifier: Intended Audience :: Information Technology
Classifier: License :: OSI Approved :: MIT License
Classifier: Programming Language :: Python
Classifier: Programming Language :: Python :: 3 :: Only
Classifier: Programming Language :: Python :: 3.7
Classifier: Programming Language :: Python :: 3.8
Classifier: Programming Language :: Python :: 3.9
Classifier: Programming Language :: Python :: 3.10
Requires-Python: >=3.7
License-File: LICENSE
Requires-Dist: beautifulsoup4 (==4.11.1)
Requires-Dist: mkdocs (>=1.4.1)
